freemad/__init__.py
freemad/agents/__init__.py
freemad/agents/base.py
freemad/agents/bootstrap.py
freemad/agents/claude_agent.py
freemad/agents/cli_adapter.py
freemad/agents/codex_agent.py
freemad/agents/factory.py
freemad/agents/registry.py
freemad/cli.py
freemad/config.py
freemad/dashboard/__init__.py
freemad/dashboard/app.py
freemad/dashboard/templates/base.html
freemad/dashboard/templates/index.html
freemad/dashboard/templates/run.html
freemad/orchestrator.py
freemad/prompts/__init__.py
freemad/prompts/templates.py
freemad/scoring/__init__.py
freemad/scoring/scorer.py
freemad/security/__init__.py
freemad/security/redaction.py
freemad/security/secrets.py
freemad/topology/__init__.py
freemad/topology/base.py
freemad/topology/factory.py
freemad/topology/impl.py
freemad/topology/info.py
freemad/types.py
freemad/utils/__init__.py
freemad/utils/budget.py
freemad/utils/cache.py
freemad/utils/canon.py
freemad/utils/logger.py
freemad/utils/parser.py
freemad/validation/__init__.py
freemad/validation/base.py
freemad/validation/coverage.py
freemad/validation/manager.py
freemad/validation/sandbox.py
freemad/validation/security.py
freemad/validation/syntax.py
freemad-1.0.0.dist-info/METADATA
freemad-1.0.0.dist-info/WHEEL
freemad-1.0.0.dist-info/entry_points.txt
freemad-1.0.0.dist-info/licenses/LICENSE
freemad-1.0.0.dist-info/RECORD
