Metadata-Version: 2.4
Name: freemad
Version: 1.0.0
Summary: FREE-MAD Orchestrator: Consensus-Free Multi-Agent Debate with CLI adapters, transcripts, dashboard, and tests.
License: MIT License
License-File: LICENSE
Author: Jonathan Santilli
Author-email: jonathansantilli@gmail.com
Requires-Python: >=3.10
Classifier: License :: OSI Approved :: MIT License
Classifier: Programming Language :: Python :: 3
Classifier: Programming Language :: Python :: 3 :: Only
Classifier: Programming Language :: Python :: 3.10
Classifier: Programming Language :: Python :: 3.11
Classifier: Programming Language :: Python :: 3.12
Classifier: Programming Language :: Python :: 3.13
Classifier: Environment :: Console
Classifier: Environment :: Web Environment
Classifier: Framework :: FastAPI
Classifier: Intended Audience :: Developers
Classifier: Topic :: Software Development :: Libraries
Classifier: Topic :: Software Development :: Testing
Requires-Dist: Jinja2 (>=3.1.4)
Requires-Dist: PyYAML (>=6.0)
Requires-Dist: fastapi (>=0.115.0)
Requires-Dist: uvicorn[standard] (>=0.30.0)
Project-URL: Documentation, https://github.com/jonathansantilli/mad#readme
Project-URL: Homepage, https://github.com/jonathansantilli/mad
Project-URL: Issues, https://github.com/jonathansantilli/mad/issues
Project-URL: Repository, https://github.com/jonathansantilli/mad
